pyrocatto_bot/__init__.py
pyrocatto_bot/__main__.py
pyrocatto_bot/client_builder/__init__.py
pyrocatto_bot/client_builder/client_builder.py
pyrocatto_bot/filters/__init__.py
pyrocatto_bot/filters/wheel_user.py
pyrocatto_bot-4.1.0.post1.dist-info/LICENSE
pyrocatto_bot-4.1.0.post1.dist-info/METADATA
pyrocatto_bot-4.1.0.post1.dist-info/WHEEL
pyrocatto_bot-4.1.0.post1.dist-info/RECORD
