Metadata-Version: 2.1
Name: pyrocatto-bot
Version: 4.1.0.post1
Summary: A multiclient bot that leverages pyrogram's smart plugins system.
License: MIT
Author: devops117
Author-email: devops117.main@protonmail.com
Requires-Python: >=3.11,<4.0
Classifier: License :: OSI Approved :: MIT License
Classifier: Programming Language :: Python :: 3
Classifier: Programming Language :: Python :: 3.11
Provides-Extra: speedups
Requires-Dist: TgCrypto (>=1.2.5,<2.0.0) ; extra == "speedups"
Requires-Dist: attrs (>=23.1.0,<24.0.0)
Requires-Dist: click (>=8.1.3,<9.0.0)
Requires-Dist: pyrocatto-pyrogram (>=2.0.107,<3.0.0)
Requires-Dist: pyrocatto-sg[speedups] (>=0.2.0.post1,<0.3.0)
Requires-Dist: ruamel-yaml (>=0.17.32,<0.18.0)
